bettermssql/__init__.py
bettermssql-0.0.2.dist-info/LICENSE.txt
bettermssql-0.0.2.dist-info/WHEEL
bettermssql-0.0.2.dist-info/METADATA
bettermssql-0.0.2.dist-info/RECORD
