Metadata-Version: 2.1
Name: bettermssql
Version: 0.0.2
Summary: A simple and lightweight ORM that facilitate some operations on SQL Server using of pyodbc.
Keywords: better,better mssql,bettermssql
Author: matgasp
Requires-Python: >= 3.9
Classifier: License :: OSI Approved :: MIT License
Classifier: Intended Audience :: Developers
Classifier: Natural Language :: English
Classifier: Development Status :: 5 - Production/Stable
Classifier: Operating System :: Microsoft :: Windows
Classifier: Topic :: Utilities
Classifier: Programming Language :: Python :: 3.9
Classifier: Programming Language :: Python :: 3.10
Classifier: Programming Language :: Python :: 3.11
Classifier: Programming Language :: Python :: 3.12
Requires-Dist: pyodbc
Project-URL: Issues, https://github.com/matgasp/bettermssql/issues
Project-URL: Repository, https://github.com/matgasp/bettermssql
